sleurencli/__init__.py
sleurencli/sleurencli.py
sleurencli/lib/__init__.py
sleurencli/lib/bcolors.py
sleurencli/lib/config.py
sleurencli/lib/functions.py
sleurencli/lib/servers.py
sleurencli/lib/sites.py
sleurencli/lib/statistics.py
sleurencli/lib/tokens.py
sleurencli-1.0.3.data/data/share/doc/sleurencli/LICENSE
sleurencli-1.0.3.data/data/share/doc/sleurencli/README.md
sleurencli-1.0.3.data/data/share/doc/sleurencli/sleuren.ini
sleurencli-1.0.3.dist-info/LICENSE
sleurencli-1.0.3.dist-info/METADATA
sleurencli-1.0.3.dist-info/WHEEL
sleurencli-1.0.3.dist-info/entry_points.txt
sleurencli-1.0.3.dist-info/top_level.txt
sleurencli-1.0.3.dist-info/RECORD
