Metadata-Version: 2.1
Name: sleurencli
Version: 1.0.3
Summary: Sleuren CLI
Home-page: https://github.com/sleuren/slereuncli
Author: Sleuren
Author-email: hello@sleuren.com
License: MIT
Keywords: sleuren system monitoring cli
Classifier: Development Status :: 5 - Production/Stable
Classifier: Environment :: Console
Classifier: Intended Audience :: System Administrators
Classifier: License :: OSI Approved :: MIT License
Classifier: Natural Language :: English
Classifier: Operating System :: POSIX :: Linux
Classifier: Operating System :: MacOS :: MacOS X
Classifier: Programming Language :: Python :: 3.4
Classifier: Programming Language :: Python :: 3.5
Classifier: Programming Language :: Python :: 3.6
Classifier: Programming Language :: Python :: 3.7
Classifier: Programming Language :: Python :: 3.8
Classifier: Topic :: System :: Monitoring
License-File: LICENSE
Requires-Dist: configparser
Requires-Dist: prettytable
Requires-Dist: requests
